flaco-0.6.0.dist-info/METADATA
flaco-0.6.0.dist-info/WHEEL
flaco/__init__.py
flaco/flaco.cp38-win32.pyd
flaco-0.6.0.dist-info/RECORD
