Metadata-Version: 2.1
Name: flaco
Version: 0.6.0
License: Unlicense/MIT
